commmons/__init__.py
commmons/array.py
commmons/clock.py
commmons/dataclass.py
commmons/dictionary.py
commmons/fs.py
commmons/func.py
commmons/hash.py
commmons/html.py
commmons/log.py
commmons/string.py
commmons/url.py
commmons/zip.py
commmons-0.0.28.dist-info/LICENSE
commmons-0.0.28.dist-info/METADATA
commmons-0.0.28.dist-info/WHEEL
commmons-0.0.28.dist-info/top_level.txt
commmons-0.0.28.dist-info/RECORD
