Metadata-Version: 2.1
Name: commmons
Version: 0.0.28
Summary: pydash + more
Home-page: https://github.com/jaeseopark/commmons
Author: Jaeseo Park
License: UNKNOWN
Platform: UNKNOWN
Classifier: Programming Language :: Python :: 3
Classifier: Operating System :: OS Independent
Requires-Python: >=3.8
License-File: LICENSE
Requires-Dist: requests
Requires-Dist: lxml
Requires-Dist: pydash
